celery_aio_pool/__init__.py
celery_aio_pool/pool.py
celery_aio_pool/tracer.py
celery_aio_pool/types.py
celery_aio_pool-0.1.0rc7.dist-info/LICENSE
celery_aio_pool-0.1.0rc7.dist-info/METADATA
celery_aio_pool-0.1.0rc7.dist-info/WHEEL
celery_aio_pool-0.1.0rc7.dist-info/RECORD
